iTesting/__init__.py
iTesting/main.py
iTesting20210802-0.1.dist-info/METADATA
iTesting20210802-0.1.dist-info/WHEEL
iTesting20210802-0.1.dist-info/entry_points.txt
iTesting20210802-0.1.dist-info/top_level.txt
iTesting20210802-0.1.dist-info/RECORD
