Metadata-Version: 2.1
Name: iTesting20210802
Version: 0.1
Summary: This is a demo framework
Home-page: https://www.helloqa.com
Author: wuyi
Author-email: testertalk@outlook.com
License: MIT
Platform: UNKNOWN
